django_starter_toolkit/__init__.py
django_starter_toolkit/forms.py
django_starter_toolkit/utils.py
django_starter_toolkit/static/django_started_tollkit/css/sidebar.css
django_starter_toolkit/static/django_started_tollkit/css/sidebar_admin.css
django_starter_toolkit/static/django_started_tollkit/css/sidebar_perfil.css
django_starter_toolkit/static/django_started_tollkit/css/style.css
django_starter_toolkit/static/django_started_tollkit/js/functions.js
django_starter_toolkit/static/django_started_tollkit/js/iconpicker.js
django_starter_toolkit/static/django_started_tollkit/js/sidebar.js
django_starter_toolkit/static/django_started_tollkit/js/sidebar_perfil.js
django_starter_toolkit-0.1.0.dist-info/LICENSE
django_starter_toolkit-0.1.0.dist-info/METADATA
django_starter_toolkit-0.1.0.dist-info/WHEEL
django_starter_toolkit-0.1.0.dist-info/top_level.txt
django_starter_toolkit-0.1.0.dist-info/RECORD
